opencv_python-4.10.0.84.dist-info/RECORD
opencv_python-4.10.0.84.dist-info/WHEEL
opencv_python-4.10.0.84.dist-info/LICENSE-3RD-PARTY.txt
opencv_python-4.10.0.84.dist-info/top_level.txt
opencv_python-4.10.0.84.dist-info/LICENSE.txt
opencv_python-4.10.0.84.dist-info/METADATA
cv2/libOrbbecSDK.1.9.dylib
cv2/config.py
cv2/version.py
cv2/libOrbbecSDK.1.9.4.dylib
cv2/__init__.pyi
cv2/__init__.py
cv2/LICENSE-3RD-PARTY.txt
cv2/load_config_py3.py
cv2/libOrbbecSDK.dylib
cv2/config-3.py
cv2/py.typed
cv2/load_config_py2.py
cv2/LICENSE.txt
cv2/cv2.abi3.so
cv2/misc/version.py
cv2/misc/__init__.py
cv2/aruco/__init__.pyi
cv2/mat_wrapper/__init__.py
cv2/parallel/__init__.pyi
cv2/flann/__init__.pyi
cv2/segmentation/__init__.pyi
cv2/cuda/__init__.pyi
cv2/gapi/__init__.pyi
cv2/gapi/__init__.py
cv2/gapi/oak/__init__.pyi
cv2/gapi/video/__init__.pyi
cv2/gapi/core/__init__.pyi
cv2/gapi/core/cpu/__init__.pyi
cv2/gapi/core/fluid/__init__.pyi
cv2/gapi/core/ocl/__init__.pyi
cv2/gapi/onnx/__init__.pyi
cv2/gapi/onnx/ep/__init__.pyi
cv2/gapi/imgproc/__init__.pyi
cv2/gapi/imgproc/fluid/__init__.pyi
cv2/gapi/ov/__init__.pyi
cv2/gapi/render/__init__.pyi
cv2/gapi/render/ocv/__init__.pyi
cv2/gapi/streaming/__init__.pyi
cv2/gapi/ot/__init__.pyi
cv2/gapi/ot/cpu/__init__.pyi
cv2/gapi/own/__init__.pyi
cv2/gapi/own/detail/__init__.pyi
cv2/gapi/ie/__init__.pyi
cv2/gapi/ie/detail/__init__.pyi
cv2/gapi/wip/__init__.pyi
cv2/gapi/wip/gst/__init__.pyi
cv2/gapi/wip/onevpl/__init__.pyi
cv2/gapi/wip/draw/__init__.pyi
cv2/utils/__init__.pyi
cv2/utils/__init__.py
cv2/utils/nested/__init__.pyi
cv2/utils/fs/__init__.pyi
cv2/.dylibs/libtheoraenc.1.dylib
cv2/.dylibs/libmbedcrypto.3.5.1.dylib
cv2/.dylibs/libp11-kit.0.dylib
cv2/.dylibs/libvmaf.1.dylib
cv2/.dylibs/libsodium.26.dylib
cv2/.dylibs/libhwy.1.0.7.dylib
cv2/.dylibs/libvorbisenc.2.dylib
cv2/.dylibs/libavcodec.60.3.100.dylib
cv2/.dylibs/libgnutls.30.dylib
cv2/.dylibs/libx264.164.dylib
cv2/.dylibs/libswscale.7.1.100.dylib
cv2/.dylibs/libtasn1.6.dylib
cv2/.dylibs/libsoxr.0.1.2.dylib
cv2/.dylibs/libjxl.0.8.2.dylib
cv2/.dylibs/libdav1d.7.dylib
cv2/.dylibs/libidn2.0.dylib
cv2/.dylibs/libaom.3.8.0.dylib
cv2/.dylibs/libcjson.1.7.17.dylib
cv2/.dylibs/libX11.6.dylib
